__init__.py
singlestore_source.py
singlestore_bytewax_connector-0.0.1.dist-info/LICENSE
singlestore_bytewax_connector-0.0.1.dist-info/METADATA
singlestore_bytewax_connector-0.0.1.dist-info/WHEEL
singlestore_bytewax_connector-0.0.1.dist-info/top_level.txt
singlestore_bytewax_connector-0.0.1.dist-info/RECORD
