Metadata-Version: 2.1
Name: singlestore-bytewax-connector
Version: 0.0.1
Summary: A Bytewax connector for SingleStore
Author-email: Tom Kühl <hello@tomkuehl.io>
Maintainer-email: Tom Kühl <hello@tomkuehl.io>
Project-URL: Homepage, https://github.com/tomkuehl/singlestore-bytewax-connector
Project-URL: Bug Reports, https://github.com/tomkuehl/singlestore-bytewax-connector/issues
Project-URL: Source, https://github.com/tomkuehl/singlestore-bytewax-connector/
Keywords: bytewax,streaming,connector,singlestore
Classifier: Development Status :: 3 - Alpha
Classifier: Intended Audience :: Developers
Classifier: License :: OSI Approved :: Apache Software License
Classifier: Programming Language :: Python :: 3
Classifier: Programming Language :: Python :: 3.7
Classifier: Programming Language :: Python :: 3.8
Classifier: Programming Language :: Python :: 3.9
Classifier: Programming Language :: Python :: 3.10
Classifier: Programming Language :: Python :: 3.11
Classifier: Programming Language :: Python :: 3 :: Only
Requires-Python: >=3.8
License-File: LICENSE
Requires-Dist: bytewax ==0.20.1
Requires-Dist: asyncmy ==0.2.9
Requires-Dist: asyncio ==3.4.3
Provides-Extra: dev
Requires-Dist: check-manifest ==0.49 ; extra == 'dev'
Requires-Dist: black ==24.4.2 ; extra == 'dev'
Requires-Dist: pre-commit >=2.19.0 ; extra == 'dev'
Requires-Dist: pytest ==8.2.2 ; extra == 'dev'
Requires-Dist: tox ==4.15.1 ; extra == 'dev'
Requires-Dist: sphinx <8 ; extra == 'dev'
Requires-Dist: sphinx-rtd-theme ; extra == 'dev'
